{"status":"success","message":"The COVERAGE field for indicator 5-6-1, translated into all languages","data":{"en":" <p> Data are available every 5 years and can be disaggregated by specific age group, rural and urban area of residence, province, education level, employment and wealth quintile </p>","pt":"<p>Os dados são disponibilizados de 5 em 5 anos e podem ser desagregados por grupo específico de idade, área de residencia rural e urbana, província, nível de escolaridade, emprego e quintil de riqueza</p>"}}