{"status":"success","message":"The SDG_TARGET field for indicator 3-c-1, translated into all languages","data":{"en":" <p> 3.c. Substantially increase health financing and recruitment, development and training, and retention of health personnel in developing countries, especially in least developed countries and small island developing states </p>","pt":"<p>3.c. Aumentar substancialmente o financiamento da sa&#xFA;de e o recrutamento, desenvolvimento e forma&#xE7;&#xE3;o, e reten&#xE7;&#xE3;o do pessoal de sa&#xFA;de nos pa&#xED;ses em desenvolvimento, especialmente nos pa&#xED;ses menos desenvolvidos e nos pequenos Estados insulares em desenvolvimento</p>"}}