<?xml version="1.0" encoding="utf-8"?>
<root>
	<status>success</status>
	<message>The REC_USE_LIM field for indicator 6-5-1, translated into all languages</message>
	<data>
		<languages>
			<language lang="en"> &lt;p&gt; Consolidation is still necessary in relation to related basin committees as the management of basins / aquifers is still in the initial stage of implementation and operationalization. &lt;/p&gt;
			</language>
			<language lang="pt">&lt;p&gt;A consolida&amp;#xE7;&amp;#xE3;o ainda &amp;#xE9; necess&amp;#xE1;ria em rela&amp;#xE7;&amp;#xE3;o a comit&amp;#xEA;s de bacia relacionados pois a gest&amp;#xE3;o de bacias/ aqu&amp;#xED;feros ainda est&amp;#xE1; em est&amp;#xE1;gio inicial de implementa&amp;#xE7;&amp;#xE3;o e operacionaliza&amp;#xE7;&amp;#xE3;o.&lt;/p&gt;
			</language>
</languages>
</data>
</root>
