<?xml version="1.0" encoding="utf-8"?>
<root>
	<status>success</status>
	<message>The STAT_CONC_DEF field for indicator 6-2-1, translated into all languages</message>
	<data>
		<languages>
			<language lang="en"> &lt;p&gt; Proportion of the population using safe managed sanitation services. &lt;/p&gt;
 &lt;p&gt; It is considered safe sanitation, basic sanitation facilities that are not shared with other families and where excreta are safely discarded on the spot or treated outside the place, such as: flush toilets inside the house, flush toilet outside the house, toilet without flush toilet, improved latrine, improved traditional latrine. &lt;/p&gt;
			</language>
			<language lang="pt">&lt;p&gt;Propor&amp;#xE7;&amp;#xE3;o da popula&amp;#xE7;&amp;#xE3;o que usa servi&amp;#xE7;os de saneamento geridos de forma segura. &lt;/p&gt;
&lt;p&gt;&amp;#xC9; considerada saneamento seguro, instala&amp;#xE7;&amp;#xF5;es de saneamento b&amp;#xE1;sicos que n&amp;#xE3;o s&amp;#xE3;o compartilhadas com outras fam&amp;#xED;lias e onde os excrementos s&amp;#xE3;o descartados com seguran&amp;#xE7;a no local ou tratados fora do local, tais como: retretes com autoclismo dentre de casa, retrete com autoclismo fora de casa, retrete sem autoclismo, latrina melhorada, latrina tradicional melhorada.&lt;/p&gt;
			</language>
</languages>
</data>
</root>
