<?xml version="1.0" encoding="utf-8"?>
<mes:GenericMetadata xmlns:mes="http://www.sdmx.org/resources/sdmxml/schemas/v2_1/message" xmlns:gen="http://www.sdmx.org/resources/sdmxml/schemas/v2_1/metadata/generic" xmlns:com="http://www.sdmx.org/resources/sdmxml/schemas/v2_1/common">
  <mes:Header>
    <mes:ID>MESSAGE_ID_PLACEHOLDER</mes:ID>
    <mes:Test>false</mes:Test>
    <mes:Prepared>2021-05-29T23:31:26.718Z</mes:Prepared>
    <mes:Sender id="sender"/>
    <mes:Structure structureID="MDS1">
      <com:Structure>
        <URN>urn:sdmx:org.sdmx.infomodel.metadatastructure.MetadataStructure=IAEG-SDGs:SDG_MSD(0.3)</URN>
      </com:Structure>
    </mes:Structure>
  </mes:Header>
  <mes:MetadataSet structureRef="MDS1" setID="dcc7a652-5ed1-4036-8f43-063d21cdc7d3">
    <com:Name xml:lang="pt">SDG METADATA SET</com:Name>
    <gen:Report id="SDG_META_RPT">
      <gen:Target id="KEY_TARGET">
        <gen:ReferenceValue id="DIMENSION_DESCRIPTOR_VALUES_TARGET">
          <gen:DataKey>
            <com:KeyValue id="SERIES">
              <com:Value>SG_LGL_GENEQLFP</com:Value>
            </com:KeyValue>
            <com:KeyValue id="REPORTING_TYPE">
              <com:Value>G</com:Value>
            </com:KeyValue>
            <com:KeyValue id="REF_AREA">
              <com:Value>508</com:Value>
            </com:KeyValue>
          </gen:DataKey>
        </gen:ReferenceValue>
        <gen:ReferenceValue id="Dataflow">
          <gen:ObjectReference>
            <URN>urn:sdmx:org.sdmx.infomodel.datastructure.Dataflow=IAEG-SDGs:DF_SDG_GLH(1.0)</URN>
          </gen:ObjectReference>
        </gen:ReferenceValue>
      </gen:Target>
      <gen:AttributeSet>
        <gen:ReportedAttribute id="ORGANISATION_UNIT">
          <com:Text xml:lang="pt"><![CDATA[<p>Direc&#xE7;&#xE3;o de Planifica&#xE7;&#xE3;o e Coopera&#xE7;&#xE3;o</p>]]></com:Text>
        </gen:ReportedAttribute>
        <gen:ReportedAttribute id="SDG_INDICATOR_INFO">
          <com:Text xml:lang="pt"/>
        </gen:ReportedAttribute>
        <gen:ReportedAttribute id="CONTACT">
          <com:Text xml:lang="pt"/>
        </gen:ReportedAttribute>
        <gen:ReportedAttribute id="IND_DEF_CON_CLASS">
          <com:Text xml:lang="pt"/>
        </gen:ReportedAttribute>
        <gen:ReportedAttribute id="SRC_TYPE_COLL_METHOD">
          <com:Text xml:lang="pt"/>
        </gen:ReportedAttribute>
        <gen:ReportedAttribute id="OTHER_METHOD">
          <com:Text xml:lang="pt"/>
        </gen:ReportedAttribute>
        <gen:ReportedAttribute id="SDG_GOAL">
          <com:Text xml:lang="pt"><![CDATA[<p>5. Alcan&#xE7;ar a igualdade de g&#xE9;nero e empoderar todas as mulheres e raparigas</p>]]></com:Text>
        </gen:ReportedAttribute>
        <gen:ReportedAttribute id="SDG_TARGET">
          <com:Text xml:lang="pt"><![CDATA[<p>5.1 Acabar com todas as formas de discrimina&#xE7;&#xE3;o contra todas as mulheres e raparigas em toda parte</p>]]></com:Text>
        </gen:ReportedAttribute>
        <gen:ReportedAttribute id="SDG_INDICATOR">
          <com:Text xml:lang="pt"><![CDATA[<h1>5.1.1 Exist&#xEA;ncia ou n&#xE3;o de quadros jur&#xED;dicos para promover, aplicar e monitorar a igualdade e a n&#xE3;o discrimina&#xE7;&#xE3;o com base no sexo </h1>]]></com:Text>
        </gen:ReportedAttribute>
        <gen:ReportedAttribute id="SDG_SERIES_DESCR">
          <com:Text xml:lang="pt"><![CDATA[<p>5.1.1 Quadros jur&#xED;dicos para promover, aplicar e monitorar a igualdade e a n&#xE3;o discrimina&#xE7;&#xE3;o com base no sexo, existente ou n&#xE3;o.</p>]]></com:Text>
        </gen:ReportedAttribute>
        <gen:ReportedAttribute id="META_LAST_UPDATE">
          <com:Text xml:lang="pt"><![CDATA[<p>03/10/2020</p>]]></com:Text>
        </gen:ReportedAttribute>
        <gen:ReportedAttribute id="SDG_RELATED_INDICATORS">
          <com:Text xml:lang="pt"><![CDATA[<p>Nenhum indicador relacionado</p>]]></com:Text>
        </gen:ReportedAttribute>
        <gen:ReportedAttribute id="CONTACT_ORGANISATION">
          <com:Text xml:lang="pt"><![CDATA[<p>Minist&#xE9;rio do G&#xE9;nero, Crian&#xE7;a e Ac&#xE7;&#xE3;o Social</p>]]></com:Text>
        </gen:ReportedAttribute>
        <gen:ReportedAttribute id="CONTACT_NAME">
          <com:Text xml:lang="pt"><![CDATA[<p>&#xC2;ngelo Tivane e Arnaldo Muthemba</p>]]></com:Text>
        </gen:ReportedAttribute>
        <gen:ReportedAttribute id="CONTACT_FUNCT">
          <com:Text xml:lang="pt"><![CDATA[<p>Chefe do Departamento de Planifica&#xE7;&#xE3;o; T&#xE9;cnico da &#xE1;rea de Estat&#xED;stica</p>]]></com:Text>
        </gen:ReportedAttribute>
        <gen:ReportedAttribute id="CONTACT_PHONE">
          <com:Text xml:lang="pt"><![CDATA[<p>+258 828351430; +258 840560048; </p>
<p> +258 826081976; +258 842268933</p>]]></com:Text>
        </gen:ReportedAttribute>
        <gen:ReportedAttribute id="CONTACT_MAIL">
          <com:Text xml:lang="pt"><![CDATA[<p><a href="mailto:Angelotivane2011@gmail.com">Angelotivane2011@gmail.com</a>; <a href="mailto:muthembarnaldo@gmail.com" target="_blank">muthembarnaldo@gmail.com</a></p>]]></com:Text>
        </gen:ReportedAttribute>
        <gen:ReportedAttribute id="CONTACT_EMAIL">
          <com:Text xml:lang="pt"><![CDATA[<p><a href="mailto:Angelotivane2011@gmail.com">Angelotivane2011@gmail.com</a>; <a href="mailto:muthembarnaldo@gmail.com" target="_blank">muthembarnaldo@gmail.com</a></p>]]></com:Text>
        </gen:ReportedAttribute>
        <gen:ReportedAttribute id="STAT_CONC_DEF">
          <com:Text xml:lang="pt"><![CDATA[<p>O indicador mede os esfor&#xE7;os do governo para estabelecer quadros legais que promovam, apliquem e monitorem a igualdade de g&#xE9;nero.</p>
<p>O indicador &#xE9; baseado numa avalia&#xE7;&#xE3;o de quadros legais que promovem, apliquem e monitoram a igualdade de g&#xE9;nero</p>]]></com:Text>
        </gen:ReportedAttribute>
        <gen:ReportedAttribute id="UNIT_MEASURE">
          <com:Text xml:lang="pt"><![CDATA[<p>Percentagem</p>]]></com:Text>
        </gen:ReportedAttribute>
        <gen:ReportedAttribute id="SOURCE_TYPE">
          <com:Text xml:lang="pt"><![CDATA[<p>Fonte administrativa. Minist&#xE9;rio da Justi&#xE7;a, Assuntos Constitucionais e Religiosos e o Minist&#xE9;rio do G&#xE9;nero, Crian&#xE7;a e Ac&#xE7;&#xE3;o Social</p>]]></com:Text>
        </gen:ReportedAttribute>
        <gen:ReportedAttribute id="COLL_METHOD">
          <com:Text xml:lang="pt"><![CDATA[<p>O Minist&#xE9;rio do G&#xE9;nero, Crian&#xE7;a e Ac&#xE7;&#xE3;o Social fez o levantamento da legisla&#xE7;&#xE3;o existente sobre a mat&#xE9;ria e actualiza anualmente, respondeu as quest&#xF5;es e procede ao c&#xE1;lculo conforme os procedimentos internacionais.</p>]]></com:Text>
        </gen:ReportedAttribute>
        <gen:ReportedAttribute id="FREQ_COLL">
          <com:Text xml:lang="pt"><![CDATA[<p>Mar&#xE7;o de 2020 </p>]]></com:Text>
        </gen:ReportedAttribute>
        <gen:ReportedAttribute id="REL_CAL_POLICY">
          <com:Text xml:lang="pt"><![CDATA[<p>Abril de 2020</p>]]></com:Text>
        </gen:ReportedAttribute>
        <gen:ReportedAttribute id="DATA_SOURCE">
          <com:Text xml:lang="pt"><![CDATA[<p> Minist&#xE9;rio da Justi&#xE7;a, Assuntos Constitucionais e Religiosos e o Minist&#xE9;rio do G&#xE9;nero, Crian&#xE7;a e Ac&#xE7;&#xE3;o Social </p>]]></com:Text>
        </gen:ReportedAttribute>
        <gen:ReportedAttribute id="COMPILING_ORG">
          <com:Text xml:lang="pt"><![CDATA[<p>Minist&#xE9;rio do G&#xE9;nero, Crian&#xE7;a e Ac&#xE7;&#xE3;o Social</p>]]></com:Text>
        </gen:ReportedAttribute>
        <gen:ReportedAttribute id="INST_MANDATE">
          <com:Text xml:lang="pt"><![CDATA[<p>Decreto Presidencial n&#xBA; 9/2015, de 13 Mar&#xE7;o, Resolu&#xE7;&#xE3;o n&#xBA; 18/2015, de 10 de Julho; Diploma Ministerial n&#xBA; 117/2015, de 31 de Dezembro;</p>]]></com:Text>
        </gen:ReportedAttribute>
        <gen:ReportedAttribute id="RATIONALE">
          <com:Text xml:lang="pt"><![CDATA[<p>O indicador tem como base o uso do question&#xE1;rio composto por 45 perguntas de respostas &#x201C;sim/n&#xE3;o&#x201D; em quatro &#xE1;reas do direito: (i) Quadros legais abrangentes e vida p&#xFA;blica; (ii) viol&#xEA;ncia contra a mulher; (iii) emprego e benef&#xED;cios econ&#xF3;micos; e (iv) casamento e fam&#xED;lia.</p>]]></com:Text>
        </gen:ReportedAttribute>
        <gen:ReportedAttribute id="REC_USE_LIM">
          <com:Text xml:lang="pt"><![CDATA[<p>O indicador &#xE9; fi&#xE1;vel, pois os dados s&#xE3;o recolhidos na fonte a n&#xED;vel nacional e &#xE9; compar&#xE1;vel internacionalmente.</p>]]></com:Text>
        </gen:ReportedAttribute>
        <gen:ReportedAttribute id="DATA_COMP">
          <com:Text xml:lang="pt"><![CDATA[<p>O indicador &#xE9; baseado na avalia&#xE7;&#xE3;o de quadros legais que promovem, aplicam e monitoram a igualdade de g&#xE9;nero usando um question&#xE1;rio composto por 45 perguntas de resposta bin&#xE1;ria &#x201C;Sim/N&#xE3;o&#x201D; em quatro &#xE1;reas do direito, extra&#xED;das do quadro jur&#xED;dico e pol&#xED;tico internacional sobre igualdade de g&#xE9;nero, em particular, a CEDAW e o Plataforma de Ac&#xE7;&#xE3;o de Pequim </p>
<p>As respostas para as perguntas s&#xE3;o codificadas com respostas simples &quot;Sim/N&#xE3;o&quot;, com &quot;1&quot; para &quot;Sim&quot; e &quot;0&quot; para &quot;N&#xE3;o&quot;. Apenas para as perguntas 1 e 2, elas podem ser pontuadas como &quot;N/A&quot;, caso em que n&#xE3;o s&#xE3;o inclu&#xED;das como parte do c&#xE1;lculo geral da pontua&#xE7;&#xE3;o para a &#xE1;rea<sup><a href="#footnote-2" id="footnote-ref-2">[2]</a></sup>. </p>
<p>A metodologia de pontua&#xE7;&#xE3;o &#xE9; a m&#xE9;dia n&#xE3;o ponderada das perguntas em cada &#xE1;rea do direito, calculada da seguinte forma:</p>
<p> .</p>
<p>Onde A<sub>i</sub> se refere &#xE0; &#xE1;rea do direito <strong>i</strong>; m<sub>i</sub> refere-se ao n&#xFA;mero total de perguntas na &#xE1;rea da lei <strong>i</strong>;<sup><a href="#footnote-3" id="footnote-ref-3">[3]</a></sup> q<sub>1</sub> + ... + q<sub>mi</sub> refere-se &#xE0; soma das perguntas codificadas na &#xE1;rea jur&#xED;dica e onde q<sub>i</sub> = &#x201D;1&#x201D; se a resposta for &#x201C;Sim&#x201D; e q<sub>i</sub> = &#x201D;0&#x201D; se a resposta for &#x201C;N&#xE3;o&#x201D;.</p>
<p>Os resultados das quatro &#xE1;reas s&#xE3;o reportados em percentagens como um painel: (A<sub>1</sub>, A<sub>2</sub>, A<sub>3</sub>, A<sub>4</sub>). A pontua&#xE7;&#xE3;o para cada &#xE1;rea (um n&#xFA;mero entre 0 e 100) representa, portanto, a percentagem de realiza&#xE7;&#xF5;es desse pa&#xED;s nessa &#xE1;rea, com 100 sendo as melhores pr&#xE1;ticas atendidas em todas as perguntas da &#xE1;rea. A escolha de apresentar todas as quatro pontua&#xE7;&#xF5;es da &#xE1;rea sem agrega&#xE7;&#xE3;o adicional &#xE9; o resultado da adop&#xE7;&#xE3;o da postura de que valores altos numa &#xE1;rea em determinado pa&#xED;s n&#xE3;o precisam compensar de forma alguma o pa&#xED;s com valores baixos em alguma outra &#xE1;rea e que um exame abrangente do valor desses quatro n&#xFA;meros para cada pa&#xED;s &#xE9; potencialmente mais informativo do que tentar resumir todos os quatro n&#xFA;meros em um &#xFA;nico &#xED;ndice.</p><div class="footnotes"><div><sup class="footnote-number" id="footnote-2">2</sup><p> Para as perguntas 1 e 2, a metodologia n&#xE3;o atribui uma pontua&#xE7;&#xE3;o (positiva ou negativa) &#xE0; exist&#xEA;ncia de direito consuetudin&#xE1;rio ou pessoal, mas pontua se elas est&#xE3;o sujeitas aos princ&#xED;pios constitucionais de igualdade ou n&#xE3;o discrimina&#xE7;&#xE3;o. Portanto, em pa&#xED;ses onde o direito consuetudin&#xE1;rio ou pessoal n&#xE3;o se aplica, essas perguntas s&#xE3;o classificadas como &quot;N/A&quot; e n&#xE3;o s&#xE3;o inclu&#xED;das como parte do c&#xE1;lculo geral da pontua&#xE7;&#xE3;o para a &#xE1;rea &apos;marcos legais abrangentes e vida p&#xFA;blica&apos;. <a href="#footnote-ref-2">&#x2191;</a></p></div><div><sup class="footnote-number" id="footnote-3">3</sup><p> Se uma pergunta for codificada como &quot;N/A&quot;, ela n&#xE3;o ser&#xE1; contada no n&#xFA;mero total de perguntas em uma &#xE1;rea da lei. <a href="#footnote-ref-3">&#x2191;</a></p></div></div>]]></com:Text>
        </gen:ReportedAttribute>
        <gen:ReportedAttribute id="DATA_VALIDATION">
          <com:Text xml:lang="pt"><![CDATA[<p>Valida&#xE7;&#xE3;o e feita pelo colectivo pela dire&#xE7;&#xE3;o nacional do g&#xE9;nero depois pelo conselho tecnico e consultivo</p>]]></com:Text>
        </gen:ReportedAttribute>
        <gen:ReportedAttribute id="DOC_METHOD">
          <com:Text xml:lang="pt"><![CDATA[<p> O m&#xE9;todo usado &#xE9; de acordo com padr&#xF5;es internacionais de medi&#xE7;&#xE3;o deste indicador</p>]]></com:Text>
        </gen:ReportedAttribute>
        <gen:ReportedAttribute id="QUALITY_MGMNT">
          <com:Text xml:lang="pt"><![CDATA[<p>Os dados s&#xE3;o analisados pela equipa de Reparti&#xE7;&#xE3;o de Monitoria e Avalia&#xE7;&#xE3;o, pelo chefe do Departamento de Planifica&#xE7;&#xE3;o, pelo Director de planifica&#xE7;&#xE3;o e coopera&#xE7;&#xE3;o, pelo Conselho Tecnico e por fim pelo Conselho Consultivo do Minist&#xE9;rio do G&#xE9;nero, Crian&#xE7;a e Ac&#xE7;&#xE3;o Social</p>]]></com:Text>
        </gen:ReportedAttribute>
        <gen:ReportedAttribute id="QUALITY_ASSURE">
          <com:Text xml:lang="pt"><![CDATA[<p>Trabalhar com pontos focais do g&#xE9;nero dos sectores contribui para a qualidade das respostas dadas das perguntas 45 perguntas que concorrem para o c&#xE1;lculo do indicador</p>]]></com:Text>
        </gen:ReportedAttribute>
        <gen:ReportedAttribute id="QUALITY_ASSMNT">
          <com:Text xml:lang="pt"><![CDATA[<p>O Minist&#xE9;rio do G&#xE9;nero, Crian&#xE7;a e Ac&#xE7;&#xE3;o Social esta organizar a &#xE1;rea de estat&#xED;stica para trabalhar em coordena&#xE7;&#xE3;o com o Instituto Nacional de Estat&#xED;stica (INE) na melhoria da qualidade de todo processo desde a recolha de dados at&#xE9; a publica&#xE7;&#xE3;o de dados.</p>]]></com:Text>
        </gen:ReportedAttribute>
        <gen:ReportedAttribute id="COVERAGE">
          <com:Text xml:lang="pt"><![CDATA[<p>Os dados est&#xE3;o desagregado em Quatro &#xE1;reas do direito: (i) quadros legais abrangentes e vida p&#xFA;blica; (ii) viol&#xEA;ncia contra a mulher; (iii) emprego e benef&#xED;cios econ&#xF3;micos; e (iv) casamento e fam&#xED;lia.</p>]]></com:Text>
        </gen:ReportedAttribute>
        <gen:ReportedAttribute id="COMPARABILITY">
          <com:Text xml:lang="pt"><![CDATA[<p>Este indicador &#xE9; global e pode ser comparado com os outros pa&#xED;ses. </p>]]></com:Text>
        </gen:ReportedAttribute>
        <gen:ReportedAttribute id="OTHER_DOC">
          <com:Text xml:lang="pt"><![CDATA[<p>www.mgcas.mz.co</p>]]></com:Text>
        </gen:ReportedAttribute>
      </gen:AttributeSet>
    </gen:Report>
  </mes:MetadataSet>
</mes:GenericMetadata>