{"status":"success","message":"The QUALITY_MGMNT field for indicator 3-3-3, translated into all languages","data":{"en":" <p> Indicators from various national and global guiding documents have been mapped and incorporated into a single framework of sector indicators to facilitate monitoring and evaluation of the performance and commitments of government and cooperation partners. At the same time, in the scope of strengthening the information system, the process of establishing interoperability between information systems in the sector is underway with a view to maximizing production, fluidity, availability, accessibility, visibility, analysis of global information data for the decision making. </p>","pt":"<p>Foram mapeados indicadores de v&#xE1;rios documentos orientadores nacionais e globais e incorporados num quadro &#xFA;nico de indicadores do sector, para facilitar a monitoria e avalia&#xE7;&#xE3;o do desempenho e compromissos do governo e parceiros de coopera&#xE7;&#xE3;o. Paralelamente, no &#xE2;mbito do fortalecimento do sistema de informa&#xE7;&#xE3;o, est&#xE1; em curso o processo de estabelecimento de interoperabilidade entre os sistemas de informa&#xE7;&#xE3;o no sector com vista a maximizar a produ&#xE7;&#xE3;o, fluidez, disponibilidade, acessibilidade, visibilidade, an&#xE1;lise de dados global da informa&#xE7;&#xE3;o para a tomada de decis&#xE3;o.</p>"}}