{"status":"success","message":"The SDG_TARGET field for indicator 3-a-1, translated into all languages","data":{"en":" <p> 3.a Strengthen the implementation of the Framework Convention on Tobacco Control in all countries, as appropriate by 2030, ensure that all girls and boys complete free, equitable and quality primary and secondary education that leads to results relevant and effective learning processes </p>","pt":"<p>3.a Fortalecer a implementação da Convenção-Quadro para o Controle do Tabaco em todos os países, conforme apropriado até 2030, garantir que todas as meninas e meninos completem o ensino primário e secundário livre, equitativo e de qualidade, que conduza a resultados de aprendizagem relevantes e eficazes</p>"}}